{
  "email": "dveloperbobby@gmail.com",
  "links": [
    {
      "url": "https://www.linkedin.com/in/developer-bobby-690074263/",
      "title": "LinkedIn",
      "icon": "LinkedInIcon"
    },
    {
      "url": "https://github.com/CodeWizarz",
      "title": "GitHub",
      "icon": "GithubIcon"
    }
  ],
  "cv": {
    "file": "codewizz.cv-1.pdf",
    "title": "Download CV",
    "label": "CV"
  },
  "description": [
    "Frontend developer heavily influenced by  interactions, and UX. Addicted to music, visual arts, and games.",
    "From India, based in Bangalore."
  ],
  "subtitles": ["he/him"],
  "skills": [
    ["Web app", "Strategic thinking", "C-S side Exp"],
    ["Frontend", "UX/UI"],
    [
      "JavaScript",
      "CSS",
      "HTML",
      "React",
      "Vue",
      "Node",
      "SVG"
    
    ],
    ["Figma", "Blender"]
  ],
  "experiences": [
    {
      "position": "Lead Frontend Engineer",
      "company": "Proof Of Memes",
      "time": "2022-2023"
    }
    
  ],
  "languages": {
    "fluent": [
      ["en-US", "English"],
      ["pt-BR", "German"]
    ],
    "intermediate": [["es-ES", "Español"]],
    "basic": [
      ["de-DE", "Deutsch"],
      ["ca-ES", "Català"]
    ]
  },
  "busy": ["Pet my cat", "Light guitar", "Games", "#olá", "Hallo"]
}
